CHANGES.txt
LICENSE.txt
MANIFEST.in
README.rst
requirements.txt
setup.py
Photohash.egg-info/PKG-INFO
Photohash.egg-info/SOURCES.txt
Photohash.egg-info/dependency_links.txt
Photohash.egg-info/requires.txt
Photohash.egg-info/top_level.txt
photohash/__init__.py
photohash/photohash.py
photohash/tests/__init__.py
photohash/tests/test_photohash.py