Metadata-Version: 1.1
Name: Photohash
Version: 0.4.0
Summary: A Python Perceptual Image Hashing Module
Home-page: https://github.com/bunchesofdonald/photohash
Author: Chris Pickett
Author-email: chris.pickett@gmail.com
License: MIT
Platform: UNKNOWN
Classifier: Development Status :: 4 - Beta
Classifier: Intended Audience :: Developers
Classifier: License :: OSI Approved :: MIT License
Classifier: Operating System :: OS Independent
Classifier: Programming Language :: Python
Classifier: Programming Language :: Python :: 2
Classifier: Programming Language :: Python :: 3
Classifier: Topic :: Scientific/Engineering :: Image Recognition
